phonexia_gender_identification_client.py
phonexia_gender_identification_client-2.0.1.dist-info/METADATA
phonexia_gender_identification_client-2.0.1.dist-info/WHEEL
phonexia_gender_identification_client-2.0.1.dist-info/entry_points.txt
phonexia_gender_identification_client-2.0.1.dist-info/top_level.txt
phonexia_gender_identification_client-2.0.1.dist-info/RECORD
